<?xml version="1.0" encoding="UTF-8"?>
<metadata xml:lang="en"><Esri><CreaDate>20150927</CreaDate><CreaTime>11123500</CreaTime><ArcGISFormat>1.0</ArcGISFormat><SyncOnce>TRUE</SyncOnce><DataProperties><lineage><Process ToolSource="c:\software\arcgis\desktop10.3\ArcToolbox\Toolboxes\Data Management Tools.tbx\DeleteField" Date="20150927" Time="111235">DeleteField Zscore_CT FID_1;CTUID_1;CTNAME_1;CMAUID_1;CMANAME_1;CMATYPE_1;CMAPUID_1;PRUID_1;PRNAME_1;OID1;GEOGRAPH_1;AVERAGE_HO;TFvariable;FID_12;CTUID_12;CTNAME_12;CMAUID_12;CMANAME_12;CMATYPE_12;CMAPUID_12;PRUID_12;PRNAME_12;OID1_1;GEOGRAPH_2;IN_THE_LAB;UNEMPLOYED;TFvariab_1;FID_12_13;CTUID_1_13;CTNAME__13;CMAUID__13;CMANAME_13;CMATYPE_13;CMAPUID_13;PRUID_1_13;PRNAME__13;OID1_12;GEOGRAPH_3;TOTAL_NU4;RENTER;TFvariab_2;FID_12__14;CTUID_1_14;CTNAME__14;CMAUID__14;CMANAME_14;CMATYPE_14;CMAPUID_14;PRUID_1_14;PRNAME__14;OID1_12_13;GEOGRAPH_4;PREVALENCE;TFvariab_3;FID_12__15;CTUID_1_15;CTNAME__15;CMAUID__15;CMANAME_15;CMATYPE_15;CMAPUID_15;PRUID_1_15;PRNAME__15;OID1_12_14;GEOGRAPH_5;GOVERNMENT;TFvariab_4;FID_12__16;CTUID_1_16;CTNAME__16;CMAUID__16;CMANAME_16;CMATYPE_16;CMAPUID_16;PRUID_1_16;PRNAME__16;OID1_12_15;GEOGRAPH_6;AVERAGE_VA;TFvariab_5;FID_12__17;CTUID_1_17;CTNAME__17;CMAUID__17;CMANAME_17;CMATYPE_17;CMAPUID_17;PRUID_1_17;PRNAME__17;OID1_12_16;GEOGRAPH_7;TOTAL_POP1;2006_TO_20;TFvariab_6;FID_12__18;CTUID_1_18;CTNAME__18;CMAUID__18;CMANAME_18;CMATYPE_18;CMAPUID_18;PRUID_1_18;PRNAME__18;OID1_12_17;GEOGRAPH_8;TOTAL_NUMB;TOTAL_LONE;TFvariab_7;FID_12__19;CTUID_1_19;CTNAME__19;CMAUID__19;CMANAME_19;CMATYPE_19;CMAPUID_19;PRUID_1_19;PRNAME__19;OID1_12_18;GEOGRAPH_9;KNOWLEDGE_;NEITHER_EN;TFvariab_8;FID_12__20;CTUID_1_20;CTNAME__20;CMAUID__20;CMANAME_20;CMATYPE_20;CMAPUID_20;PRUID_1_20;PRNAME__20;OID1_12_19;GEOGRAP_10;TOTAL_PO_1;CANADIAN_C;TFvariab_9;FID_12__21;CTUID_1_21;CTNAME__21;CMAUID__21;CMANAME_21;CMATYPE_21;CMAPUID_21;PRUID_1_21;PRNAME__21;OID1_12_20;GEOGRAP_11;TOTAL_NU3;LIVING_AL1;TFvaria_10;FID_12__22;CTUID_1_22;CTNAME__22;CMAUID__22;CMANAME_22;CMATYPE_22;CMAPUID_22;PRUID_1_22;PRNAME__22;OID1_12_21;GEOGRAP_12;TOTAL_NU_1;MAJOR_REPA;TFvaria_11;FID_12__23;CTUID_1_23;CTNAME__23;CMAUID__23;CMANAME_23;CMATYPE_23;CMAPUID_23;PRUID_1_23;PRNAME__23;OID1_12_22;GEOGRAP_13;TOTAL_NU5;MOVABLE_DW;TFvaria_12;FID_12__24;CTUID_1_24;CTNAME__24;CMAUID__24;CMANAME_24;CMATYPE_24;CMAPUID_24;PRUID_1_24;PRNAME__24;OID1_12_23;GEOGRAP_14;TOTAL_NUM1;1960_OR_BE;TFvaria_13</Process><Process ToolSource="c:\software\arcgis\desktop10.3\ArcToolbox\Toolboxes\Data Management Tools.tbx\CalculateField" Date="20150927" Time="113338">CalculateField Zscore_CT Z_HAI [Z_score] VB #</Process><Process ToolSource="c:\software\arcgis\desktop10.3\ArcToolbox\Toolboxes\Data Management Tools.tbx\CalculateField" Date="20150927" Time="113345">CalculateField Zscore_CT Z_LU [Z_score_1] VB #</Process><Process ToolSource="c:\software\arcgis\desktop10.3\ArcToolbox\Toolboxes\Data Management Tools.tbx\CalculateField" Date="20150927" Time="113355">CalculateField Zscore_CT Z_DR [Z_score_12] VB #</Process><Process ToolSource="c:\software\arcgis\desktop10.3\ArcToolbox\Toolboxes\Data Management Tools.tbx\CalculateField" Date="20150927" Time="113405">CalculateField Zscore_CT Z_LI [Z_score_13] VB #</Process><Process ToolSource="c:\software\arcgis\desktop10.3\ArcToolbox\Toolboxes\Data Management Tools.tbx\CalculateField" Date="20150927" Time="113419">CalculateField Zscore_CT Z_GT [Z_score_14] VB #</Process><Process ToolSource="c:\software\arcgis\desktop10.3\ArcToolbox\Toolboxes\Data Management Tools.tbx\CalculateField" Date="20150927" Time="113429">CalculateField Zscore_CT Z_DAV [Z_score_15] VB #</Process><Process ToolSource="c:\software\arcgis\desktop10.3\ArcToolbox\Toolboxes\Data Management Tools.tbx\CalculateField" Date="20150927" Time="113438">CalculateField Zscore_CT Z_I [Z_score_16] VB #</Process><Process ToolSource="c:\software\arcgis\desktop10.3\ArcToolbox\Toolboxes\Data Management Tools.tbx\CalculateField" Date="20150927" Time="113446">CalculateField Zscore_CT Z_LP [Z_score_17] VB #</Process><Process ToolSource="c:\software\arcgis\desktop10.3\ArcToolbox\Toolboxes\Data Management Tools.tbx\CalculateField" Date="20150927" Time="113454">CalculateField Zscore_CT Z_NL [Z_score_18] VB #</Process><Process ToolSource="c:\software\arcgis\desktop10.3\ArcToolbox\Toolboxes\Data Management Tools.tbx\CalculateField" Date="20150927" Time="113503">CalculateField Zscore_CT Z_CC [Z_score_19] VB #</Process><Process ToolSource="c:\software\arcgis\desktop10.3\ArcToolbox\Toolboxes\Data Management Tools.tbx\CalculateField" Date="20150927" Time="113511">CalculateField Zscore_CT Z_LA [Z_score_20] VB #</Process><Process ToolSource="c:\software\arcgis\desktop10.3\ArcToolbox\Toolboxes\Data Management Tools.tbx\CalculateField" Date="20150927" Time="113519">CalculateField Zscore_CT Z_DMR [Z_score_21] VB #</Process><Process ToolSource="c:\software\arcgis\desktop10.3\ArcToolbox\Toolboxes\Data Management Tools.tbx\CalculateField" Date="20150927" Time="113527">CalculateField Zscore_CT Z_DM [Z_score_22] VB #</Process><Process ToolSource="c:\software\arcgis\desktop10.3\ArcToolbox\Toolboxes\Data Management Tools.tbx\CalculateField" Date="20150927" Time="113534">CalculateField Zscore_CT Z_1960C [Z_score_23] VB #</Process><Process ToolSource="c:\software\arcgis\desktop10.3\ArcToolbox\Toolboxes\Data Management Tools.tbx\DeleteField" Date="20150927" Time="113610">DeleteField Zscore_CT Z_score;Z_score_1;Z_score_12;Z_score_13;Z_score_14;Z_score_15;Z_score_16;Z_score_17;Z_score_18;Z_score_19;Z_score_20;Z_score_21;Z_score_22;Z_score_23</Process><Process ToolSource="c:\software\arcgis\desktop10.3\ArcToolbox\Toolboxes\Data Management Tools.tbx\CalculateField" Date="20150927" Time="151012">CalculateField Zscore_CT ID [GEOGRAPHY] VB #</Process></lineage></DataProperties></Esri></metadata>
